	{
		"name": "Global Information",
		"numberOfRequests": {
			"total": 1214,
			"ok": 1214,
			"ko": 0
		},
		"minResponseTime": {
			"total": 80,
			"ok": 80,
			"ko": -1
		},
		"maxResponseTime": {
			"total": 640,
			"ok": 640,
			"ko": -1
		},
		"meanResponseTime": {
			"total": 146,
			"ok": 146,
			"ko": -1
		},
		"standardDeviation": {
			"total": 48,
			"ok": 48,
			"ko": -1
		},
		"percentiles1": {
			"total": 200,
			"ok": 200,
			"ko": -1
		},
		"percentiles2": {
			"total": 220,
			"ok": 220,
			"ko": -1
		},
		"group1": {
			"name": "t < 800 ms",
			"count": 1214,
			"percentage": 100
		},
		"group2": {
			"name": "800 ms < t < 1200 ms",
			"count": 0,
			"percentage": 0
		},
		"group3": {
			"name": "t > 1200 ms",
			"count": 0,
			"percentage": 0
		},
		"group4": {
			"name": "failed",
			"count": 0,
			"percentage": 0
		},
		"meanNumberOfRequestsPerSecond": {
			"total": 40,
			"ok": 40,
			"ko": -1
		}
	}