	{
		"name": "Global Information",
		"numberOfRequests": {
			"total": 1368,
			"ok": 1368,
			"ko": 0
		},
		"minResponseTime": {
			"total": 30,
			"ok": 30,
			"ko": -1
		},
		"maxResponseTime": {
			"total": 12740,
			"ok": 12740,
			"ko": -1
		},
		"meanResponseTime": {
			"total": 2215,
			"ok": 2215,
			"ko": -1
		},
		"standardDeviation": {
			"total": 2994,
			"ok": 2994,
			"ko": -1
		},
		"percentiles1": {
			"total": 12480,
			"ok": 12480,
			"ko": -1
		},
		"percentiles2": {
			"total": 12630,
			"ok": 12630,
			"ko": -1
		},
		"group1": {
			"name": "t < 800 ms",
			"count": 299,
			"percentage": 21
		},
		"group2": {
			"name": "800 ms < t < 1200 ms",
			"count": 203,
			"percentage": 14
		},
		"group3": {
			"name": "t > 1200 ms",
			"count": 866,
			"percentage": 63
		},
		"group4": {
			"name": "failed",
			"count": 0,
			"percentage": 0
		},
		"meanNumberOfRequestsPerSecond": {
			"total": 44,
			"ok": 44,
			"ko": -1
		}
	}